[
  [0, {"timeContainerCaption": "USPresidents", "timeObjectRefServerList": [
      {"TOType": "timeData",      "Database": "dbAcademy",     "DatabaseKey": 11},
      {"TOType": "timeData",      "Database": "dbAcademy",     "DatabaseKey": 12},
      {"TOType": "timeData",      "Database": "dbAcademy",     "DatabaseKey": 13},
      {"TOType": "timeData",      "Database": "dbAcademy",     "DatabaseKey": 14},
      {"TOType": "timeData",      "Database": "dbAcademy",     "DatabaseKey": 15},
      {"TOType": "timeData",      "Database": "dbAcademy",     "DatabaseKey": 16},
      {"TOType": "timeData",      "Database": "dbAcademy",     "DatabaseKey": 17},
      {"TOType": "timeData",      "Database": "dbAcademy",     "DatabaseKey": 18},
      {"TOType": "timeData",      "Database": "dbAcademy",     "DatabaseKey": 19},
      {"TOType": "timeData",      "Database": "dbAcademy",     "DatabaseKey": 20},
      {"TOType": "timeData",      "Database": "dbAcademy",     "DatabaseKey": 21},
      {"TOType": "timeData",      "Database": "dbAcademy",     "DatabaseKey": 22},
      {"TOType": "timeData",      "Database": "dbAcademy",     "DatabaseKey": 23},
      {"TOType": "timeData",      "Database": "dbAcademy",     "DatabaseKey": 24},
      {"TOType": "timeData",      "Database": "dbAcademy",     "DatabaseKey": 25},
      {"TOType": "timeData",      "Database": "dbAcademy",     "DatabaseKey": 26},
      {"TOType": "timeData",      "Database": "dbAcademy",     "DatabaseKey": 27},
      {"TOType": "timeData",      "Database": "dbAcademy",     "DatabaseKey": 28},
      {"TOType": "timeData",      "Database": "dbAcademy",     "DatabaseKey": 29},
      {"TOType": "timeData",      "Database": "dbAcademy",     "DatabaseKey": 30},
      {"TOType": "timeData",      "Database": "dbAcademy",     "DatabaseKey": 31},
      {"TOType": "timeData",      "Database": "dbAcademy",     "DatabaseKey": 32},
      {"TOType": "timeData",      "Database": "dbAcademy",     "DatabaseKey": 33},
      {"TOType": "timeData",      "Database": "dbAcademy",     "DatabaseKey": 34},
      {"TOType": "timeData",      "Database": "dbAcademy",     "DatabaseKey": 35},
      {"TOType": "timeData",      "Database": "dbAcademy",     "DatabaseKey": 36},
      {"TOType": "timeData",      "Database": "dbAcademy",     "DatabaseKey": 37},
      {"TOType": "timeData",      "Database": "dbAcademy",     "DatabaseKey": 38},
      {"TOType": "timeData",      "Database": "dbAcademy",     "DatabaseKey": 39},
      {"TOType": "timeData",      "Database": "dbAcademy",     "DatabaseKey": 40},
      {"TOType": "timeData",      "Database": "dbAcademy",     "DatabaseKey": 41},
      {"TOType": "timeData",      "Database": "dbAcademy",     "DatabaseKey": 42},
      {"TOType": "timeData",      "Database": "dbAcademy",     "DatabaseKey": 43},
      {"TOType": "timeData",      "Database": "dbAcademy",     "DatabaseKey": 44},
      {"TOType": "timeData",      "Database": "dbAcademy",     "DatabaseKey": 45},
      {"TOType": "timeData",      "Database": "dbAcademy",     "DatabaseKey": 46},
      {"TOType": "timeData",      "Database": "dbAcademy",     "DatabaseKey": 47},
      {"TOType": "timeData",      "Database": "dbAcademy",     "DatabaseKey": 48},
      {"TOType": "timeData",      "Database": "dbAcademy",     "DatabaseKey": 49},
      {"TOType": "timeData",      "Database": "dbAcademy",     "DatabaseKey": 50},
      {"TOType": "timeData",      "Database": "dbAcademy",     "DatabaseKey": 51},
      {"TOType": "timeData",      "Database": "dbAcademy",     "DatabaseKey": 52},
      {"TOType": "timeData",      "Database": "dbAcademy",     "DatabaseKey": 53},
      {"TOType": "timeData",      "Database": "dbAcademy",     "DatabaseKey": 54},
      {"TOType": "timeData",      "Database": "dbAcademy",     "DatabaseKey": 55}
    ]}],
  [1, {"timeContainerCaption": "26datas", "timeObjectRefServerList": [
      {"TOType": "timeData",      "Database": "dbAcademy",     "DatabaseKey": 0},
      {"TOType": "timeData",      "Database": "dbAcademy",     "DatabaseKey": 1},
      {"TOType": "timeData",      "Database": "dbAcademy",     "DatabaseKey": 2},
      {"TOType": "timeData",      "Database": "dbAcademy",     "DatabaseKey": 3},
      {"TOType": "timeData",      "Database": "dbAcademy",     "DatabaseKey": 4},
      {"TOType": "timeData",      "Database": "dbAcademy",     "DatabaseKey": 5},
      {"TOType": "timeData",      "Database": "dbAcademy",     "DatabaseKey": 6},
      {"TOType": "timeData",      "Database": "dbAcademy",     "DatabaseKey": 7},
      {"TOType": "timeData",      "Database": "dbAcademy",     "DatabaseKey": 8},
      {"TOType": "timeData",      "Database": "dbUserAccount", "DatabaseKey": 0},
      {"TOType": "timeData",      "Database": "dbUserAccount", "DatabaseKey": 1},
      {"TOType": "timeData",      "Database": "dbUserAccount", "DatabaseKey": 2},
      {"TOType": "timeData",      "Database": "dbUserAccount", "DatabaseKey": 3},
      {"TOType": "timeData",      "Database": "dbAcademy",     "DatabaseKey": 0},
      {"TOType": "timeData",      "Database": "dbAcademy",     "DatabaseKey": 1},
      {"TOType": "timeData",      "Database": "dbAcademy",     "DatabaseKey": 2},
      {"TOType": "timeData",      "Database": "dbAcademy",     "DatabaseKey": 3},
      {"TOType": "timeData",      "Database": "dbAcademy",     "DatabaseKey": 4},
      {"TOType": "timeData",      "Database": "dbAcademy",     "DatabaseKey": 5},
      {"TOType": "timeData",      "Database": "dbAcademy",     "DatabaseKey": 6},
      {"TOType": "timeData",      "Database": "dbAcademy",     "DatabaseKey": 7},
      {"TOType": "timeData",      "Database": "dbAcademy",     "DatabaseKey": 8},
      {"TOType": "timeData",      "Database": "dbUserAccount", "DatabaseKey": 0},
      {"TOType": "timeData",      "Database": "dbUserAccount", "DatabaseKey": 1},
      {"TOType": "timeData",      "Database": "dbUserAccount", "DatabaseKey": 2},
      {"TOType": "timeData",      "Database": "dbUserAccount", "DatabaseKey": 3}
    ]}],
  [2, {"timeContainerCaption": "13datas", "timeObjectRefServerList": [
      {"TOType": "timeData",      "Database": "dbAcademy",     "DatabaseKey": 0},
      {"TOType": "timeData",      "Database": "dbAcademy",     "DatabaseKey": 1},
      {"TOType": "timeData",      "Database": "dbAcademy",     "DatabaseKey": 2},
      {"TOType": "timeData",      "Database": "dbAcademy",     "DatabaseKey": 3},
      {"TOType": "timeData",      "Database": "dbAcademy",     "DatabaseKey": 4},
      {"TOType": "timeData",      "Database": "dbAcademy",     "DatabaseKey": 5},
      {"TOType": "timeData",      "Database": "dbAcademy",     "DatabaseKey": 6},
      {"TOType": "timeData",      "Database": "dbAcademy",     "DatabaseKey": 7},
      {"TOType": "timeData",      "Database": "dbAcademy",     "DatabaseKey": 8},
      {"TOType": "timeData",      "Database": "dbUserAccount", "DatabaseKey": 0},
      {"TOType": "timeData",      "Database": "dbUserAccount", "DatabaseKey": 1},
      {"TOType": "timeData",      "Database": "dbUserAccount", "DatabaseKey": 2},
      {"TOType": "timeData",      "Database": "dbUserAccount", "DatabaseKey": 3}
    ]}],
  [3, {"timeContainerCaption": "7datas", "timeObjectRefServerList": [
      {"TOType": "timeData",      "Database": "dbAcademy",     "DatabaseKey": 0},
      {"TOType": "timeData",      "Database": "dbAcademy",     "DatabaseKey": 1},
      {"TOType": "timeData",      "Database": "dbAcademy",     "DatabaseKey": 2},
      {"TOType": "timeData",      "Database": "dbAcademy",     "DatabaseKey": 7},
      {"TOType": "timeData",      "Database": "dbAcademy",     "DatabaseKey": 8},
      {"TOType": "timeData",      "Database": "dbUserAccount", "DatabaseKey": 0},
      {"TOType": "timeData",      "Database": "dbUserAccount", "DatabaseKey": 1}
    ]}],
  [4, {"timeContainerCaption": "5datas 2containers", "timeObjectRefServerList": [
      {"TOType": "timeData",      "Database": "dbAcademy",     "DatabaseKey": 0},
      {"TOType": "timeData",      "Database": "dbAcademy",     "DatabaseKey": 1},
      {"TOType": "timeData",      "Database": "dbAcademy",     "DatabaseKey": 2},
      {"TOType": "timeData",      "Database": "dbAcademy",     "DatabaseKey": 7},
      {"TOType": "timeData",      "Database": "dbAcademy",     "DatabaseKey": 8},
      {"TOType": "timeData",      "Database": "dbUserAccount", "DatabaseKey": 0},
      {"TOType": "timeData",      "Database": "dbUserAccount", "DatabaseKey": 1}
    ]}]
]
